intreg/__init__.py
intreg/intreg.py
intreg/meintreg.py
intreg-0.2.2.dist-info/licenses/LICENSE
intreg-0.2.2.dist-info/METADATA
intreg-0.2.2.dist-info/WHEEL
intreg-0.2.2.dist-info/top_level.txt
intreg-0.2.2.dist-info/RECORD
