Metadata-Version: 2.4
Name: intreg
Version: 0.2.2
Summary: A package for fitting an interval and mixed effect interval regression model to censored and/or uncensored point and/or interval data
Author: Philip W Fowler
Author-email: Dylan Adlard <dylan.adlard@ndm.ox.ac.uk>
License: MIT
Project-URL: Homepage, https://github.com/fowler-lab/intreg
Keywords: interval regression,mixed effects
Classifier: Programming Language :: Python :: 3
Requires-Python: >=3.9
License-File: LICENSE
Requires-Dist: numpy
Requires-Dist: scipy
Dynamic: license-file
